asoid/__init__.py
asoid/__main__.py
asoid/app.py
asoid/categories.py
asoid/utilities.py
asoid/.streamlit/config.toml
asoid/apps/A_data_preprocess.py
asoid/apps/B_extract_features.py
asoid/apps/C_auto_active_learning.py
asoid/apps/D_manual_active_learning.py
asoid/apps/E_predict.py
asoid/apps/F_view.py
asoid/apps/G_unsupervised_discovery.py
asoid/apps/__init__.py
asoid/config/__init__.py
asoid/config/default_config.ini
asoid/config/global_config.py
asoid/config/help_messages.py
asoid/config/streamlit_config.ini
asoid/images/GUI_overview.png
asoid/images/active_learning.png
asoid/images/active_learning_schematic.png
asoid/images/app_discovery.png
asoid/images/asoid_logo (1).ico
asoid/images/asoid_logo.png
asoid/images/asoid_logo_wtext.png
asoid/images/baseline_classifier.png
asoid/images/baseline_classifier_wht.png
asoid/images/baseline_prediction.png
asoid/images/data_process.png
asoid/images/data_process_wht.png
asoid/images/feature_extraction.png
asoid/images/feature_extraction_wht.png
asoid/ui/__init__.py
asoid/utils/__init__.py
asoid/utils/auto_active_learning.py
asoid/utils/extract_features.py
asoid/utils/import_data.py
asoid/utils/load_css.py
asoid/utils/load_preprocess.py
asoid/utils/load_workspace.py
asoid/utils/manual_active_learning.py
asoid/utils/motionenergy.py
asoid/utils/predict_new_data.py
asoid/utils/preprocessing.py
asoid/utils/project_utils.py
asoid/utils/unsupervised_discovery.py
asoid/utils/view_results.py
asoid/utils/visuals.py
asoid-0.3b9.dist-info/LICENSE
asoid-0.3b9.dist-info/METADATA
asoid-0.3b9.dist-info/WHEEL
asoid-0.3b9.dist-info/entry_points.txt
asoid-0.3b9.dist-info/top_level.txt
asoid-0.3b9.dist-info/RECORD
