Metadata-Version: 2.1
Name: asoid
Version: 0.3b9
Summary: ASOiD: An active learning approach to behavioral classification
Home-page: https://github.com/YttriLab/A-SOID
Author: ['Jens F. Schweihoff', 'Alexander Hsu']
License: BSD 3-Clause License
Project-URL: Documentation, https://github.com/YttriLab/A-SOID
Project-URL: Bug Tracker, https://github.com/YttriLab/A-SOID/issues
Keywords: Active learning,pose estimation,behavior analysis,neuroscience
Requires-Python: >=3.7
License-File: LICENSE
Requires-Dist: click
Requires-Dist: ipython
Requires-Dist: setuptools
Requires-Dist: psutil
Requires-Dist: streamlit
Requires-Dist: streamlit-option-menu
Requires-Dist: hydralit
Requires-Dist: numpy
Requires-Dist: pandas
Requires-Dist: joblib
Requires-Dist: matplotlib
Requires-Dist: seaborn
Requires-Dist: scikit-learn
Requires-Dist: h5py
Requires-Dist: plotly
Requires-Dist: tqdm
Requires-Dist: stqdm
Requires-Dist: numba
Requires-Dist: scipy
Requires-Dist: moviepy
Requires-Dist: pillow
Requires-Dist: opencv-python
Requires-Dist: umap-learn
Requires-Dist: hdbscan
